{
"type": "FeatureCollection",
"crs": { "type": "name", "properties": { "name": "urn:ogc:def:crs:OGC:1.3:CRS84" } },
                                                                                
"features": [
{ "type": "Feature", "properties": { "id": 1 }, "geometry": { "type": "Point", "coordinates": [-123.23326,45.43600] } },
{ "type": "Feature", "properties": { "id": 1 }, "geometry": { "type": "Point", "coordinates": [-123.234992,45.442920] } }
]
}
